GoogleMailLibrary/GoogleMailLibrary.py
GoogleMailLibrary/__init__.py
rf_googlemaillibrary-1.0.8.dist-info/METADATA
rf_googlemaillibrary-1.0.8.dist-info/WHEEL
rf_googlemaillibrary-1.0.8.dist-info/top_level.txt
rf_googlemaillibrary-1.0.8.dist-info/RECORD
