Metadata-Version: 2.1
Name: rf-googlemaillibrary
Version: 1.0.8
Summary: Google Mail Library
Home-page: https://mainsystemdev.github.io/GoogleMailLibrary
Author: Francisco G. Quinola
Author-email: francisco.quinola@mnltechnology.com
License: Type license() to see the full license text
Platform: any
Classifier: Development Status :: 5 - Production/Stable
Classifier: License :: OSI Approved :: MIT License
Classifier: Operating System :: OS Independent
Classifier: Programming Language :: Python :: 3
Classifier: Topic :: Software Development :: Testing
Classifier: Framework :: Robot Framework
Classifier: Framework :: Robot Framework :: Library
Requires-Dist: google-api-python-client
Requires-Dist: google-auth
Requires-Dist: google-auth-httplib2
Requires-Dist: google-auth-oauthlib
Requires-Dist: html2text
Requires-Dist: oauth2client
Requires-Dist: robotframework-pythonlibcore (>=3.0.0)
Requires-Dist: robotframework-seleniumlibrary (>=4.5.0)
Requires-Dist: robotframework (>=5.0.0)
